com/__init__.py
com/zwf/__init__.py
com/zwf/ModelDemo/Data.py
com/zwf/ModelDemo/NetConn.py
com/zwf/ModelDemo/__init__.py
com/zwf/container/BackBag.py
com/zwf/container/DynamicCode.py
com/zwf/container/Extends.py
com/zwf/container/HashCode.py
com/zwf/container/InnerClass.py
com/zwf/container/InnerMethod.py
com/zwf/container/InstanceClass.py
com/zwf/container/LambdaDemo.py
com/zwf/container/OOPDemo.py
com/zwf/container/OOPDemo1.py
com/zwf/container/__init__.py
com/zwf/container/forDemo.py
com/zwf/container/lazyLoad.py
com/zwf/container/publicVariable.py
com/zwf/container/recursionDemo.py
com/zwf/container/varityRegion.py
com/zwf/demo/CallBackMethod.py
com/zwf/demo/DataType.py
com/zwf/demo/DataTypeDemo.py
com/zwf/demo/DataTypeInput.py
com/zwf/demo/DateTimeDemo.py
com/zwf/demo/DefineException.py
com/zwf/demo/DeleteMethon.py
com/zwf/demo/EnumDemo.py
com/zwf/demo/EnumDemo2.py
com/zwf/demo/ExceptionDemo.py
com/zwf/demo/GetFactory.py
com/zwf/demo/ListMake.py
com/zwf/demo/LottoDemo.py
com/zwf/demo/ObjectEqual.py
com/zwf/demo/ProxyClass.py
com/zwf/demo/ProxyMode.py
com/zwf/demo/RaiseException.py
com/zwf/demo/RcDemo.py
com/zwf/demo/SetDemo.py
com/zwf/demo/StaticMethod.py
com/zwf/demo/__init__.py
com/zwf/demo/defMethods.py
com/zwf/demo/defMethods1.py
com/zwf/demo/defMethods2.py
com/zwf/demo/dequeDemo.py
com/zwf/demo/dict_demo.py
com/zwf/demo/formatDemo.py
com/zwf/demo/helloWord.py
com/zwf/demo/inputDemo.py
com/zwf/demo/printDemo.py
com/zwf/demo/sequceCount.py
com/zwf/demo/sequenceDemo.py
com/zwf/demo/testDemo.py
com/zwf/demo/tuple_demo.py
python_study_demo-1.0.1.dist-info/METADATA
python_study_demo-1.0.1.dist-info/WHEEL
python_study_demo-1.0.1.dist-info/top_level.txt
python_study_demo-1.0.1.dist-info/RECORD
