Metadata-Version: 2.1
Name: python_study_demo
Version: 1.0.1
Summary: 这是一个学习Demo代码集
Home-page: http://www.baidu.com
Author: 小曾
Classifier: Environment :: Web Environment
Classifier: Intended Audience :: Developers
Classifier: License :: OSI Approved :: BSD License
Classifier: Operating System :: OS Independent
Classifier: Programming Language :: Python
Classifier: Programming Language :: Python :: 2
Classifier: Programming Language :: Python :: 3
